MANIFEST.in
setup.py
beim/__init__.py
beim/__init__.pyc
beim/bzrrepoutils.py
beim/bzrrepoutils.pyc
beim/datastore.py
beim/datastore.pyc
beim/dir_tree.py
beim/logger.py
beim/logger.pyc
beim/osutils.py
beim/osutils.pyc
beim/repoutils.py
beim/svnrepoutils.py
beim/svnrepoutils.pyc
beim.egg-info/PKG-INFO
beim.egg-info/SOURCES.txt
beim.egg-info/dependency_links.txt
beim.egg-info/entry_points.txt
beim.egg-info/top_level.txt
beim/binary_release/webinstall.py
beim/build/BuildDirs.py
beim/build/BuildDirs.pyc
beim/build/Make.mm.template
beim/build/__init__.py
beim/build/__init__.pyc
beim/build/build.py
beim/build/build.pyc
beim/build/generate_Makemm.py
beim/build/generate_Makemm.pyc
beim/build/generate_dottools.py
beim/build/generate_dottools.pyc
beim/envvars/__init__.py
beim/envvars/__init__.pyc
beim/envvars/operations/__init__.py
beim/envvars/operations/__init__.pyc
beim/envvars/renderers/BashScriptor.py
beim/envvars/renderers/BashScriptor.pyc
beim/envvars/renderers/Performer.py
beim/envvars/renderers/__init__.py
beim/envvars/renderers/__init__.pyc
beim/install/__init__.py
beim/installers/__init__.py
beim/installers/__init__.pyc
beim/installers/download.py
beim/installers/download.pyc
beim/installers/easy_install_support.py
beim/installers/misc.py
beim/installers/src.py
beim/installers/src.pyc
beim/installers/HDF4/__init__.py
beim/installers/HDF4/src.py
beim/installers/HDF5/__init__.py
beim/installers/HDF5/src.py
beim/installers/boostpython/__init__.py
beim/installers/boostpython/src.py
beim/installers/h4h5tools/__init__.py
beim/installers/h4h5tools/src.py
beim/installers/matplotlib/__init__.py
beim/installers/matplotlib/src.py
beim/installers/mpich2/__init__.py
beim/installers/mpich2/src.py
beim/installers/py_cjson/__init__.py
beim/installers/py_cjson/src.py
beim/installers/py_h5py/__init__.py
beim/installers/py_h5py/src.py
beim/installers/py_numpy/__init__.py
beim/installers/py_numpy/__init__.pyc
beim/installers/py_numpy/src.py
beim/installers/py_numpy/src.pyc
beim/installers/py_psutil/__init__.py
beim/installers/py_psutil/src.py
beim/installers/pylons/__init__.py
beim/installers/pylons/src.py
