Metadata-Version: 1.1
Name: beim
Version: 0.01
Summary: beim: a release builder
Home-page: UNKNOWN
Author: Jiao Lin
Author-email: linjiao@caltech.edu
License: UNKNOWN
Download-URL: http://dev.danse.us/packages/beim-0.01.tar.gz
Platform: UNKNOWN
